{"url": "https://en.wikipedia.org/wiki/Linkin_Park_and_Friends:_Celebrate_Life_in_Honor_of_Chester_Bennington", "text": "Linkin Park and Friends: Celebrate Life in Honor of Chester Bennington Concert by Linkin Park and others Venue Hollywood Bowl Date(s) October 27, 2017 Website www.linkinpark.com\n\nLinkin Park and Friends: Celebrate Life in Honor of Chester Bennington was a tribute concert by American rock band Linkin Park. The concert was held to honor their frontman, Chester Bennington, who committed suicide on July 20, 2017. The concert took place on October 27, 2017, at the Hollywood Bowl. This was Linkin Park's first performance following Bennington's death. The concert featured various artists, including Blink-182, members of System of a Down, Korn, Avenged Sevenfold, Sum 41, Bring Me the Horizon, Civil Twilight, A Day to Remember, Yellowcard, and Kiiara.[1]\n\nBackground [ edit ]\n\nRight after the first leg of Linkin Park's One More Light World Tour, promoting their seventh studio album, One More Light, vocalist Chester Bennington was found dead from suicide by hanging on July 20, 2017, resulting in the cancellation of the rest of the tour.[2]\n\nOn August 22, Linkin Park announced plans to host a tribute concert in Los Angeles to honor Bennington.[3] Later, the band confirmed that the concert would take place on October 27 at the Hollywood Bowl, and would feature a number of bands and musicians. On September 23, the band announced that the concert had officially sold out.\n\nOn October 20, it was announced Linkin Park would livestream the concert on their YouTube channel.[4][5]\n\nPerformers [ edit ]\n\nMike Shinoda \u2013 lead and backing vocals, rapping, rhythm guitar, keyboards, piano, synthesizers, samplers, bass on \"Shadow Of The Day\" and \"With Or Without You\", lead guitar on \"Waiting For The End\"\n\nBrad Delson \u2013 lead guitar, backing vocals, lead acoustic guitar on \"Sharp Edges\", keyboards on \"Waiting For The End\", synthesizer on \"Burn It Down\", not performed on \"Castle Of Glass\" and \"Rebellion\"\n\nRob Bourdon \u2013 drums, not performed on \"Castle Of Glass\", \"Sharp Edges\", \"One More Light\", \"Crawling\", \"Rebellion\", \"What I've Done\" and \"A Light That Never Comes\"\n\nJoe Hahn \u2013 turntables, samplers, keyboards, synthesizers, backing vocals, not performed on \"Sharp Edges\".\n\nDave Farrell \u2013 bass, backing vocals, rhythm guitar on \"Shadow Of The Day\", \"With Or Without You\" and \"Leave Out All The Rest\", rhythm acoustic guitar on \"Sharp Edges\", not performed on \"Castle Of Glass\", \"Rebellion\" and \"What I've Done\" [6]\n\nSpecial guests [ edit ]\n\nSet list [ edit ]\n\nLinkin Park\n\nEncore\n\nReferences [ edit ]", "images": ["https://upload.wikimedia.org/wikipedia/commons/thumb/8/89/Symbol_book_class2.svg/16px-Symbol_book_class2.svg.png", "https://en.wikipedia.org/wiki/Special:CentralAutoLogin/start?type=1x1", "https://en.wikipedia.org/static/images/wikimedia-button.png", "https://en.wikipedia.org/static/images/poweredby_mediawiki_88x31.png", "https://en.wikipedia.org/static/apple-touch/wikipedia.png"], "top_img": "https://en.wikipedia.org/static/apple-touch/wikipedia.png", "keywords": [], "authors": [], "canonical_link": "https://en.wikipedia.org/wiki/Linkin_Park_and_Friends:_Celebrate_Life_in_Honor_of_Chester_Bennington", "title": "Linkin Park and Friends: Celebrate Life in Honor of Chester Bennington", "meta_data": {"generator": "MediaWiki 1.35.0-wmf.27", "referrer": "origin-when-cross-origin"}, "movies": [], "publish_date": null, "source": "https://en.wikipedia.org", "summary": ""}