{"url": "https://www.bbc.co.uk/bbcthree/article/b71065eb-d88f-4db4-bbc0-95d885cc4886", "text": "Frida is part of the wider rescue effort that involves thousands of volunteers and the Mexican military. Currently, thousands of people are reported injured and many others are still believed to be trapped under the rubble in Mexico City and surrounding towns.", "images": ["https://ichef.bbci.co.uk/images/ic/704xn/p05rmmyd.jpg", "https://ichef.bbci.co.uk/images/ic/704xn/p05mkvzp.jpg", "https://ichef.bbci.co.uk/images/ic/704xn/p088vzb5.jpg", "https://ichef.bbci.co.uk/images/ic/704xn/p07gh46d.jpg", "https://ichef.bbci.co.uk/images/ic/704xn/p07kq9wy.jpg", "https://ichef.bbci.co.uk/images/ic/704xn/p06z3swp.jpg", "https://ssc.api.bbc.com/?c1=2&c2=19293874&ns_site=bbc&name=", "https://ichef.bbci.co.uk/images/ic/704xn/p07kpznp.jpg", "http://b.scorecardresearch.com/p?c1=2&c2=17986528&cv=2.0&cj=1", "https://ichef.bbci.co.uk/images/ic/704xn/p07rv0p4.jpg", "https://ichef.bbci.co.uk/images/ic/704xn/p06k850w.jpg", "https://ichef.bbci.co.uk/images/ic/704xn/p088zmyd.jpg", "https://ichef.bbci.co.uk/images/ic/704x396_b/p070ckxz.jpg", "https://ichef.bbci.co.uk/images/ic/704xn/p0893270.jpg", "https://ichef.bbci.co.uk/images/ic/704xn/p07hpwyp.jpg", "https://a1.api.bbc.co.uk/hit.xiti?&col=1&from=p&ptag=js&s=598253&p=unknown&x1=[urn:bbc:isite2:b71065eb-d88f-4db4-bbc0-95d885cc4886]&x2=[responsive]&x3=[bbc_website]&x4=[en]&x7=[article]&x8=[reverb-1.4.0-nojs]&x11=[BBC_THREE]&x12=[BBC_THREE]", "https://ichef.bbci.co.uk/images/ic/704xn/p070bk7z.jpg", "https://ichef.bbci.co.uk/images/ic/704xn/p088gjjh.jpg", "https://ichef.bbci.co.uk/images/ic/704xn/p06y1zt2.jpg", "https://ichef.bbci.co.uk/images/ic/704xn/p061zvm5.jpg"], "top_img": "https://ichef.bbci.co.uk/images/ic/704xn/p05rmmyd.jpg", "keywords": [], "authors": ["Tomasz Frymorgen"], "canonical_link": "https://www.bbc.co.uk/bbcthree/article/b71065eb-d88f-4db4-bbc0-95d885cc4886", "title": "Meet Frida, Mexico\u2019s hero canine who\u2019s saved 12 lives", "meta_data": {"description": "Check out this content on BBC Three.", "viewport": "width=device-width, initial-scale=1.0", "fb": {"admins": 501067221, "profile_id": 7519460786, "app_id": 58567469885}, "og": {"site_name": "BBC Three", "locale": "en_GB", "type": "article", "title": "Meet Frida, Mexico\u2019s hero canine who\u2019s saved 12 lives - BBC Three", "description": "Check out this content on BBC Three.", "image": "https://ichef.bbci.co.uk/images/ic/704xn/p05rmmyd.jpg", "url": "https://www.bbc.co.uk/bbcthree/article/b71065eb-d88f-4db4-bbc0-95d885cc4886"}, "article": {"publisher": "https://www.facebook.com/bbcthree/", "published_time": "2017-09-22T16:52:31+00:00", "modified_time": "2017-09-22T16:52:31+00:00", "author": "Tomasz Frymorgen"}, "twitter": {"card": "summary_large_image", "site": "@bbcthree", "domain": "BBC Three", "creator": "@bbcthree"}, "msapplication-square70x70logo": "https://bbcthree-web-cdn.files.bbci.co.uk/bbcthree-web-server/2.63.10-67.x86_64/images/meta/three-76.png", "msapplication-square150x150logo": "https://bbcthree-web-cdn.files.bbci.co.uk/bbcthree-web-server/2.63.10-67.x86_64/images/meta/three-152.png"}, "movies": [], "publish_date": 1506099151.0, "source": "https://www.bbc.co.uk", "summary": ""}