{"url": "https://www.refinery29.com/en-us/2018/04/196904/taraji-p-henson-hairstylist-tym-wallace", "text": "There are some celebrities who have a \"signature look\" \u2014 like J.Lo's glow , Kim Kardashian's contour, or Gwen Stefani's red lip . But Taraji P. Henson can't be pinned down to one aesthetic. On any given week, you'll see her in glam Hollywood waves, a long wrapped ponytail, or a sharp angled bob... and it's all thanks to her mane man, Tym Wallace . Three years ago, he blew her away while doing her hair on the set of Acrimony , and Henson solidified the relationship with four words: \"You belong to me.\" Wallace happily obliged, and they've been a match made in hair heaven ever since. Ahead, learn about how he and Taraji got so close, the products he swears by, and all the wigs he carries in his 70-pound kit.", "images": ["https://www.refinery29.com/assets/d27ad8510dcf0eef13f6419f4f9a76e6.svg", "https://www.refinery29.com/assets/a899ed2b6826791e2b8dd7b2901f3668.svg", "https://www.refinery29.com/assets/563283d1407bc6df5095935bc30a3daa.svg", "https://www.refinery29.com/assets/e0a9b3381492f1a143fc3d5144778c26.svg", "https://www.refinery29.com/assets/94ef6f5acdd752723f8644874464d07a.svg", "https://www.refinery29.com/assets/94aebf5b5499306ab207a2b4f13e34a8.svg", "https://www.refinery29.com/assets/a70678be6c693f8a9915bec2fa49ee49.svg", "https://s2.r29static.com/bin/entry/0b3/0,675,2000,1050/x,80/1955994/image.jpg"], "top_img": "https://s2.r29static.com/bin/entry/0b3/0,675,2000,1050/x,80/1955994/image.jpg", "keywords": [], "authors": ["Thatiana Diaz", "Megan Decker", "Aimee Simeon", "Rachel Krause", "Erika Stalder", "Elly Belle", "The Secret Behind Taraji P Hensons Best Hair Looks Ever"], "canonical_link": "https://www.refinery29.com/en-us/2018/04/196904/taraji-p-henson-hairstylist-tym-wallace", "title": "This Is Why Taraji P. Henson's Hair Always Looks So Good", "meta_data": {"title": "The Secret Behind Taraji P Hensons Best Hair Looks Ever", "description": "Taraji P. Henson met hairstylist Tym Wallace three years ago \u2014 and hasn't looked back since.", "og": {"url": "https://www.refinery29.com/en-us/2018/04/196904/taraji-p-henson-hairstylist-tym-wallace", "title": "This Is Why Taraji P. Henson's Hair Always Looks So Good", "description": "Taraji P. Henson met hairstylist Tym Wallace three years ago \u2014 and hasn't looked back since.", "image": {"identifier": "https://s2.r29static.com/bin/entry/0b3/0,675,2000,1050/x,80/1955994/image.jpg", "secure_url": "https://s2.r29static.com/bin/entry/0b3/0,675,2000,1050/x,80/1955994/image.jpg", "width": 2000, "height": 1050}, "type": "article"}, "twitter": {"title": "This Is Why Taraji P. Henson's Hair Always Looks So Good", "card": "summary_large_image", "site": "@refinery29", "description": "Taraji P. Henson met hairstylist Tym Wallace three years ago \u2014 and hasn't looked back since.", "image": "https://s2.r29static.com/bin/entry/0b3/0,675,2000,1050/x,80/1955994/image.jpg"}, "pinterest": {"image": "https://s2.r29static.com/bin/entry/0b3/112,0,1776,2400/x,80/1955994/image.jpg"}, "fb": {"app_id": 155023867867753, "pages": "86973707921,587074007996399,269626263209765,509115739117952,1562713254009921,583745561686633,656112191237463,284423314989162,974273182666651,192477361634120"}, "article": {"publisher": "refinery29"}, "viewport": "width=device-width, initial-scale=1", "theme-color": "#fd5b4e", "news_keywords": "taraji p. henson, taraji p. henson hair, taraji p. henson style, taraji p hensen, tym wallace, tym wallace hairstyle, tym wallace taraji, taraji p. henson natural hair, taraji p. henson style, taraji p. henson makeup, taraji p. henson", "p": {"domain_verify": "b10faeb45f92f5ebf0073a215d615ea9"}, "entry_template": "entry.article", "author": "Khalea Underwood", "channel": {"tag": "short-hairstyles"}}, "movies": [], "publish_date": 1524067200.0, "source": "https://www.refinery29.com", "summary": ""}