{"url": "http://www.revelist.com/makeup/jordyn-woods-beauty-products/9013", "text": ">> Click to buy\n\n\u201cYes, I\u2019m Black, and yes, I get ashy,\u201d she said during her Refinery 29 interview. \u201cShea butter is key!\u201d\n\n\n\nFor clarity, people who are not Black get ashy as well, but I get where Jordyn was going with her statement. Shea butter is everything.\n\nJordyn didn't specify what brand she uses, but I recommend any formula that is made of 100 percent shea butter, instead of it simply being listed as a primary ingredient. Shea butter is great to rub on your entire body, scalp included. It also spreads well so you don't have to use a lot.\n\nI have a container of organic L'Occitane shea butter ($39, Sephora) that has lasted me for three months and I use it regularly.", "images": ["https://ugc.reveliststatic.com/gen/constrain/300/300/80/2020/03/31/15/33/d2/poxgzzsy2o18y.png", "https://ugc.reveliststatic.com/gen/constrain/300/300/80/2020/04/01/11/2z/bx/po2ule9a0w1bw.png", "http://b.scorecardresearch.com/p?c1=2&c2=6035453&cv=2.0&cj=1&cs_wn=", "http://pixel.quantserve.com/pixel/p-bnzfTM78T_ems.gif", "https://ugc.reveliststatic.com/gen/constrain/300/300/80/2020/03/31/12/4n/bx/poe0u0p7281bw.png", "https://ugc.reveliststatic.com/gen/constrain/300/300/80/2020/04/06/14/b7/j0/pokm5vfdc81d5.png", "https://ct.pinterest.com/v3/?tid=2616872273084&noscript=1", "https://ugc.reveliststatic.com/gen/constrain/300/300/80/2020/04/06/16/10/r9/potla43lhw1bw.png", "https://ct.pinterest.com/v3/?tid=2616872273084&event=pagevisit&noscript=1", "https://ugc.reveliststatic.com/gen/crop/62/62/80/2018/04/06/15/5u/bh/pov6dcv1k4zn.jpg", "https://ugc.reveliststatic.com/gen/constrain/300/170/80/2017/02/22/14/5o/zu/pot01si28sie.png", "http://trc.taboola.com/1215023/log/3/unip?en=view_content", "https://ugc.reveliststatic.com/gen/constrain/300/170/80/2020/04/01/11/2z/bx/po2ule9a0w1bw.png", "http://www.revelist.com/images/1x1.gif", "https://ugc.reveliststatic.com/gen/constrain/300/170/80/2020/04/06/14/b7/j0/pokm5vfdc81d5.png", "https://ugc.reveliststatic.com/gen/constrain/150/150/80/2020/04/13/15/9g/ed/poj0tx8s0s18y.png", "https://ugc.reveliststatic.com/gen/constrain/300/170/80/2020/03/31/15/33/d2/poxgzzsy2o18y.png", "https://ugc.reveliststatic.com/gen/constrain/150/150/80/2020/04/09/09/4o/j5/poxc27308w18y.png", "https://ugc.reveliststatic.com/gen/full/2017/08/23/15/70/0p/por6dscewwzn.png", "https://ugc.reveliststatic.com/gen/constrain/300/170/80/2020/03/31/12/4n/bx/poe0u0p7281bw.png", "https://ugc.reveliststatic.com/gen/constrain/300/300/80/2020/04/03/11/ew/3x/po3mcatzsc1bw.png", "https://www.facebook.com/tr?id=434351533770785&ev=PageView&noscript=1", "https://ugc.reveliststatic.com/gen/constrain/300/300/80/2016/06/13/14/f3/0x/poijvlgw009.png", "https://ugc.reveliststatic.com/gen/constrain/150/150/80/2020/04/10/16/bv/0c/poenu4loo41bw.png", "https://ugc.reveliststatic.com/gen/constrain/300/300/80/2017/02/22/14/5o/zu/pot01si28sie.png"], "top_img": "https://ugc.reveliststatic.com/gen/full/2017/08/23/15/70/0p/por6dscewwzn.png", "keywords": [], "authors": ["Aug"], "canonical_link": "https://www.revelist.com/makeup/jordyn-woods-beauty-products/9013", "title": "Jordyn Woods' 7 favorite beauty products are really unexpected", "meta_data": {"viewport": "width=device-width,initial-scale=1,minimum-scale=1.0,user-scalable=0,maximum-scale=1.0", "description": "Jordyn Woods revealed the seven beauty products she can't live without, and her beauty routine is surprisingly low-key.", "title": "These are Jordyn Woods' 7 favorite beauty products | Revelist", "og": {"site_name": "Revelist.com", "type": "article", "locale": "en_US", "title": "Jordyn Woods' 7 favorite beauty products are really unexpected", "description": "YES!", "image": {"identifier": "https://ugc.reveliststatic.com/gen/full/2017/08/23/15/70/0p/por6dscewwzn.png", "url": "https://ugc.reveliststatic.com/gen/full/2017/08/23/15/70/0p/por6dscewwzn.png", "type": "image/png", "height": 675, "width": 1200}, "url": "https://www.revelist.com/makeup/jordyn-woods-beauty-products/9013"}, "fb": {"pages": 194235290942369}, "twitter": {"card": "summary_large_image", "title": "Jordyn Woods' 7 favorite beauty products are really unexpected", "description": "YES!", "image": "https://ugc.reveliststatic.com/gen/full/2017/08/23/15/70/0p/por6dscewwzn.png", "site": "@HeyRevelist", "url": "https://www.revelist.com/makeup/jordyn-woods-beauty-products/9013"}, "lytics": {"post_type": "slideshow", "category": "Beauty", "subcategories": "Makeup", "tags": "Makeup, Beauty, BeautyHowTos, Skin, Celebrity, Entertainment,", "brand_safe": "true"}, "application-name": "", "msapplication-TileColor": "#FFFFFF", "msapplication-TileImage": "https://www.revelist.com/mstile-144x144.png", "msapplication-square70x70logo": "https://www.revelist.com/mstile-70x70.png", "msapplication-square150x150logo": "https://www.revelist.com/mstile-150x150.png", "msapplication-wide310x150logo": "https://www.revelist.com/mstile-310x150.png", "msapplication-square310x310logo": "https://www.revelist.com/mstile-310x310.png"}, "movies": [], "publish_date": null, "source": "http://www.revelist.com", "summary": ""}