{"url": "https://consequenceofsound.net/2017/07/michelle-branch-and-the-black-keys-patrick-carney-are-engaged/", "text": "Patrick Carney Michelle Branch\n\nMichelle Branch has announced her engagement to The Black Keys drummer Patrick Carney.\n\nThe pair began dating will working on Branch\u2019s recent album, Hopeless Romantic, which Carney produced. This summer they\u2019ll tour together in support of the album.\n\n\n\nCarney popped the question on Sunday night as Branch celebrated her 34th birthday. \u201cThank you for all the birthday love and wishes. Last night, right before I blew out my candles, [Carney] asked me to marry him and then I had nothing left to wish for,\u201d she wrote on Instagram. \u201c34 might be the best year yet.\u201d", "images": ["https://consequenceofsound.net/wp-content/themes/consequenceofsound/img/icon-radio-cos.svg", "https://consequenceofsound.net/wp-content/uploads/2017/07/patrick-carney-michelle-branch.png?w=807", "https://consequenceofsound.net/wp-content/themes/consequenceofsound/img/1x1.trans.gif", "https://consequenceofsound.net/wp-content/uploads/2017/07/patrick-carney-michelle-branch.png", "https://consequenceofsound.net/wp-content/uploads/2018/01/close-icon.png"], "top_img": "https://consequenceofsound.net/wp-content/uploads/2017/07/patrick-carney-michelle-branch.png", "keywords": [], "authors": ["Alex Young"], "canonical_link": "https://consequenceofsound.net/2017/07/michelle-branch-and-the-black-keys-patrick-carney-are-engaged/", "title": "Michelle Branch and The Black Keys\u2019 Patrick Carney are engaged", "meta_data": {"msvalidate.01": "8CABEAF0C9CE91FCEDBFB11C38206EE5", "fb": {"app_id": 434175690014, "pages": 19875021647}, "description": "The pair began dating while working on Branch's comeback album, Hopeless Romantic.", "robots": "max-snippet:-1, max-image-preview:large, max-video-preview:-1", "og": {"locale": "en_US", "type": "article", "title": "Michelle Branch and The Black Keys' Patrick Carney are engaged", "description": "The pair began dating while working on Branch's comeback album, Hopeless Romantic.", "url": "https://consequenceofsound.net/2017/07/michelle-branch-and-the-black-keys-patrick-carney-are-engaged/", "site_name": "Consequence of Sound", "image": {"identifier": "https://consequenceofsound.net/wp-content/uploads/2017/07/patrick-carney-michelle-branch.png", "secure_url": "https://consequenceofsound.net/wp-content/uploads/2017/07/patrick-carney-michelle-branch.png", "width": 1000, "height": 801}}, "article": {"publisher": "https://www.facebook.com/consequence/", "tag": "Romance", "section": "Entertainment News", "published_time": "2017-07-04T17:42:01-04:00", "categories": "Entertainment News"}, "twitter": {"card": "summary_large_image", "description": "The pair began dating while working on Branch's comeback album, Hopeless Romantic.", "title": "Michelle Branch and The Black Keys' Patrick Carney are engaged", "site": "@consequence", "image": "https://consequenceofsound.net/wp-content/uploads/2017/07/patrick-carney-michelle-branch.png", "creator": "@consequence"}, "generator": "WordPress 5.4", "viewport": "width=device-width, initial-scale=1, minimum-scale=1, maximum-scale=1", "apple-itunes-app": "app-id=971967886", "msapplication-TileImage": "https://consequenceofsound.net/wp-content/uploads/2019/03/cosfavicon.png?w=80"}, "movies": [], "publish_date": 1499204521.0, "source": "https://consequenceofsound.net", "summary": ""}